[
  {
    "_key": "15",
    "_id": "txn/15",
    "_rev": "_gDzJN5a---"
  },
  {
    "_key": "24",
    "_id": "txn/24",
    "_rev": "_gDzJN5a--_"
  },
  {
    "_key": "26",
    "_id": "txn/26",
    "_rev": "_gDzJN5a--A"
  },
  {
    "_key": "27",
    "_id": "txn/27",
    "_rev": "_gDzJN5a--B"
  },
  {
    "_key": "43",
    "_id": "txn/43",
    "_rev": "_gDzJN5e---"
  },
  {
    "_key": "44",
    "_id": "txn/44",
    "_rev": "_gDzJN5e--_"
  },
  {
    "_key": "49",
    "_id": "txn/49",
    "_rev": "_gDzJN5e--A"
  },
  {
    "_key": "53",
    "_id": "txn/53",
    "_rev": "_gDzJN5e--B"
  },
  {
    "_key": "54",
    "_id": "txn/54",
    "_rev": "_gDzJN5e--C"
  },
  {
    "_key": "55",
    "_id": "txn/55",
    "_rev": "_gDzJN5e--D"
  },
  {
    "_key": "58",
    "_id": "txn/58",
    "_rev": "_gDzJN5e--E"
  },
  {
    "_key": "61",
    "_id": "txn/61",
    "_rev": "_gDzJN5e--F"
  },
  {
    "_key": "65",
    "_id": "txn/65",
    "_rev": "_gDzJN5i---"
  },
  {
    "_key": "72",
    "_id": "txn/72",
    "_rev": "_gDzJN5i--_"
  },
  {
    "_key": "74",
    "_id": "txn/74",
    "_rev": "_gDzJN5i--A"
  },
  {
    "_key": "77",
    "_id": "txn/77",
    "_rev": "_gDzJN5i--B"
  },
  {
    "_key": "84",
    "_id": "txn/84",
    "_rev": "_gDzJN5i--C"
  },
  {
    "_key": "89",
    "_id": "txn/89",
    "_rev": "_gDzJN5i--D"
  },
  {
    "_key": "92",
    "_id": "txn/92",
    "_rev": "_gDzJN5i--E"
  },
  {
    "_key": "95",
    "_id": "txn/95",
    "_rev": "_gDzJN5m---"
  },
  {
    "_key": "99",
    "_id": "txn/99",
    "_rev": "_gDzJN5m--_"
  },
  {
    "_key": "105",
    "_id": "txn/105",
    "_rev": "_gDzJN5m--A"
  },
  {
    "_key": "109",
    "_id": "txn/109",
    "_rev": "_gDzJN5m--B"
  },
  {
    "_key": "118",
    "_id": "txn/118",
    "_rev": "_gDzJN5m--C"
  },
  {
    "_key": "119",
    "_id": "txn/119",
    "_rev": "_gDzJN5q---"
  },
  {
    "_key": "123",
    "_id": "txn/123",
    "_rev": "_gDzJN5q--_"
  },
  {
    "_key": "124",
    "_id": "txn/124",
    "_rev": "_gDzJN5q--A"
  },
  {
    "_key": "128",
    "_id": "txn/128",
    "_rev": "_gDzJN5q--B"
  },
  {
    "_key": "129",
    "_id": "txn/129",
    "_rev": "_gDzJN5q--C"
  },
  {
    "_key": "133",
    "_id": "txn/133",
    "_rev": "_gDzJN5q--D"
  },
  {
    "_key": "134",
    "_id": "txn/134",
    "_rev": "_gDzJN5q--E"
  },
  {
    "_key": "138",
    "_id": "txn/138",
    "_rev": "_gDzJN5u---"
  },
  {
    "_key": "144",
    "_id": "txn/144",
    "_rev": "_gDzJN5u--_"
  },
  {
    "_key": "148",
    "_id": "txn/148",
    "_rev": "_gDzJN5u--A"
  },
  {
    "_key": "153",
    "_id": "txn/153",
    "_rev": "_gDzJN5u--B"
  },
  {
    "_key": "157",
    "_id": "txn/157",
    "_rev": "_gDzJN5u--C"
  },
  {
    "_key": "160",
    "_id": "txn/160",
    "_rev": "_gDzJN5u--D"
  },
  {
    "_key": "164",
    "_id": "txn/164",
    "_rev": "_gDzJN5y---"
  },
  {
    "_key": "165",
    "_id": "txn/165",
    "_rev": "_gDzJN5y--_"
  },
  {
    "_key": "170",
    "_id": "txn/170",
    "_rev": "_gDzJN5y--A"
  },
  {
    "_key": "173",
    "_id": "txn/173",
    "_rev": "_gDzJN5y--B"
  },
  {
    "_key": "181",
    "_id": "txn/181",
    "_rev": "_gDzJN5y--C"
  },
  {
    "_key": "183",
    "_id": "txn/183",
    "_rev": "_gDzJN5y--D"
  },
  {
    "_key": "191",
    "_id": "txn/191",
    "_rev": "_gDzJN5y--E"
  },
  {
    "_key": "195",
    "_id": "txn/195",
    "_rev": "_gDzJN52---"
  },
  {
    "_key": "198",
    "_id": "txn/198",
    "_rev": "_gDzJN52--_"
  },
  {
    "_key": "202",
    "_id": "txn/202",
    "_rev": "_gDzJN52--A"
  },
  {
    "_key": "207",
    "_id": "txn/207",
    "_rev": "_gDzJN52--B"
  },
  {
    "_key": "212",
    "_id": "txn/212",
    "_rev": "_gDzJN52--C"
  },
  {
    "_key": "219",
    "_id": "txn/219",
    "_rev": "_gDzJN52--D"
  },
  {
    "_key": "227",
    "_id": "txn/227",
    "_rev": "_gDzJN52--E"
  },
  {
    "_key": "233",
    "_id": "txn/233",
    "_rev": "_gDzJN52--F"
  },
  {
    "_key": "236",
    "_id": "txn/236",
    "_rev": "_gDzJN56---"
  },
  {
    "_key": "242",
    "_id": "txn/242",
    "_rev": "_gDzJN56--_"
  },
  {
    "_key": "243",
    "_id": "txn/243",
    "_rev": "_gDzJN56--A"
  },
  {
    "_key": "251",
    "_id": "txn/251",
    "_rev": "_gDzJN56--B"
  },
  {
    "_key": "256",
    "_id": "txn/256",
    "_rev": "_gDzJN56--C"
  },
  {
    "_key": "259",
    "_id": "txn/259",
    "_rev": "_gDzJN56--D"
  },
  {
    "_key": "270",
    "_id": "txn/270",
    "_rev": "_gDzJN56--E"
  },
  {
    "_key": "274",
    "_id": "txn/274",
    "_rev": "_gDzJN6----"
  },
  {
    "_key": "278",
    "_id": "txn/278",
    "_rev": "_gDzJN6---_"
  },
  {
    "_key": "285",
    "_id": "txn/285",
    "_rev": "_gDzJN6---A"
  },
  {
    "_key": "287",
    "_id": "txn/287",
    "_rev": "_gDzJN6---B"
  },
  {
    "_key": "290",
    "_id": "txn/290",
    "_rev": "_gDzJN6---C"
  },
  {
    "_key": "294",
    "_id": "txn/294",
    "_rev": "_gDzJN6---D"
  },
  {
    "_key": "295",
    "_id": "txn/295",
    "_rev": "_gDzJN6---E"
  },
  {
    "_key": "299",
    "_id": "txn/299",
    "_rev": "_gDzJN6C---"
  },
  {
    "_key": "301",
    "_id": "txn/301",
    "_rev": "_gDzJN6C--_"
  },
  {
    "_key": "304",
    "_id": "txn/304",
    "_rev": "_gDzJN6C--A"
  },
  {
    "_key": "307",
    "_id": "txn/307",
    "_rev": "_gDzJN6C--B"
  },
  {
    "_key": "311",
    "_id": "txn/311",
    "_rev": "_gDzJN6C--C"
  },
  {
    "_key": "313",
    "_id": "txn/313",
    "_rev": "_gDzJN6G---"
  },
  {
    "_key": "316",
    "_id": "txn/316",
    "_rev": "_gDzJN6G--_"
  },
  {
    "_key": "319",
    "_id": "txn/319",
    "_rev": "_gDzJN6G--A"
  },
  {
    "_key": "323",
    "_id": "txn/323",
    "_rev": "_gDzJN6G--B"
  },
  {
    "_key": "329",
    "_id": "txn/329",
    "_rev": "_gDzJN6G--C"
  },
  {
    "_key": "342",
    "_id": "txn/342",
    "_rev": "_gDzJN6G--D"
  },
  {
    "_key": "344",
    "_id": "txn/344",
    "_rev": "_gDzJN6G--E"
  },
  {
    "_key": "350",
    "_id": "txn/350",
    "_rev": "_gDzJN6K---"
  },
  {
    "_key": "351",
    "_id": "txn/351",
    "_rev": "_gDzJN6K--_"
  },
  {
    "_key": "358",
    "_id": "txn/358",
    "_rev": "_gDzJN6K--A"
  },
  {
    "_key": "361",
    "_id": "txn/361",
    "_rev": "_gDzJN6K--B"
  },
  {
    "_key": "363",
    "_id": "txn/363",
    "_rev": "_gDzJN6K--C"
  },
  {
    "_key": "375",
    "_id": "txn/375",
    "_rev": "_gDzJN6K--D"
  },
  {
    "_key": "377",
    "_id": "txn/377",
    "_rev": "_gDzJN6K--E"
  },
  {
    "_key": "379",
    "_id": "txn/379",
    "_rev": "_gDzJN6K--F"
  },
  {
    "_key": "383",
    "_id": "txn/383",
    "_rev": "_gDzJN6K--G"
  },
  {
    "_key": "386",
    "_id": "txn/386",
    "_rev": "_gDzJN6O---"
  },
  {
    "_key": "393",
    "_id": "txn/393",
    "_rev": "_gDzJN6O--_"
  },
  {
    "_key": "396",
    "_id": "txn/396",
    "_rev": "_gDzJN6O--A"
  },
  {
    "_key": "398",
    "_id": "txn/398",
    "_rev": "_gDzJN6O--B"
  },
  {
    "_key": "401",
    "_id": "txn/401",
    "_rev": "_gDzJN6O--C"
  },
  {
    "_key": "403",
    "_id": "txn/403",
    "_rev": "_gDzJN6O--D"
  },
  {
    "_key": "407",
    "_id": "txn/407",
    "_rev": "_gDzJN6O--E"
  },
  {
    "_key": "408",
    "_id": "txn/408",
    "_rev": "_gDzJN6O--F"
  },
  {
    "_key": "417",
    "_id": "txn/417",
    "_rev": "_gDzJN6S---"
  },
  {
    "_key": "422",
    "_id": "txn/422",
    "_rev": "_gDzJN6S--_"
  },
  {
    "_key": "424",
    "_id": "txn/424",
    "_rev": "_gDzJN6S--A"
  },
  {
    "_key": "425",
    "_id": "txn/425",
    "_rev": "_gDzJN6S--B"
  },
  {
    "_key": "427",
    "_id": "txn/427",
    "_rev": "_gDzJN6S--C"
  },
  {
    "_key": "432",
    "_id": "txn/432",
    "_rev": "_gDzJN6S--D"
  },
  {
    "_key": "438",
    "_id": "txn/438",
    "_rev": "_gDzJN6S--E"
  },
  {
    "_key": "440",
    "_id": "txn/440",
    "_rev": "_gDzJN6S--F"
  },
  {
    "_key": "442",
    "_id": "txn/442",
    "_rev": "_gDzJN6W---"
  },
  {
    "_key": "450",
    "_id": "txn/450",
    "_rev": "_gDzJN6W--_"
  },
  {
    "_key": "455",
    "_id": "txn/455",
    "_rev": "_gDzJN6W--A"
  },
  {
    "_key": "456",
    "_id": "txn/456",
    "_rev": "_gDzJN6W--B"
  },
  {
    "_key": "458",
    "_id": "txn/458",
    "_rev": "_gDzJN6W--C"
  },
  {
    "_key": "461",
    "_id": "txn/461",
    "_rev": "_gDzJN6W--D"
  },
  {
    "_key": "470",
    "_id": "txn/470",
    "_rev": "_gDzJN6W--E"
  },
  {
    "_key": "476",
    "_id": "txn/476",
    "_rev": "_gDzJN6W--F"
  },
  {
    "_key": "479",
    "_id": "txn/479",
    "_rev": "_gDzJN6a---"
  },
  {
    "_key": "484",
    "_id": "txn/484",
    "_rev": "_gDzJN6a--_"
  },
  {
    "_key": "491",
    "_id": "txn/491",
    "_rev": "_gDzJN6a--A"
  },
  {
    "_key": "494",
    "_id": "txn/494",
    "_rev": "_gDzJN6a--B"
  },
  {
    "_key": "498",
    "_id": "txn/498",
    "_rev": "_gDzJN6a--C"
  },
  {
    "_key": "502",
    "_id": "txn/502",
    "_rev": "_gDzJN6a--D"
  },
  {
    "_key": "519",
    "_id": "txn/519",
    "_rev": "_gDzJN6a--E"
  },
  {
    "_key": "524",
    "_id": "txn/524",
    "_rev": "_gDzJN6a--F"
  },
  {
    "_key": "527",
    "_id": "txn/527",
    "_rev": "_gDzJN6e---"
  },
  {
    "_key": "533",
    "_id": "txn/533",
    "_rev": "_gDzJN6e--_"
  },
  {
    "_key": "534",
    "_id": "txn/534",
    "_rev": "_gDzJN6e--A"
  },
  {
    "_key": "537",
    "_id": "txn/537",
    "_rev": "_gDzJN6e--B"
  },
  {
    "_key": "544",
    "_id": "txn/544",
    "_rev": "_gDzJN6e--C"
  },
  {
    "_key": "545",
    "_id": "txn/545",
    "_rev": "_gDzJN6e--D"
  },
  {
    "_key": "552",
    "_id": "txn/552",
    "_rev": "_gDzJN6e--E"
  },
  {
    "_key": "554",
    "_id": "txn/554",
    "_rev": "_gDzJN6e--F"
  },
  {
    "_key": "557",
    "_id": "txn/557",
    "_rev": "_gDzJN6e--G"
  },
  {
    "_key": "562",
    "_id": "txn/562",
    "_rev": "_gDzJN6i---"
  },
  {
    "_key": "566",
    "_id": "txn/566",
    "_rev": "_gDzJN6i--_"
  },
  {
    "_key": "571",
    "_id": "txn/571",
    "_rev": "_gDzJN6i--A"
  },
  {
    "_key": "579",
    "_id": "txn/579",
    "_rev": "_gDzJN6i--B"
  },
  {
    "_key": "583",
    "_id": "txn/583",
    "_rev": "_gDzJN6i--C"
  },
  {
    "_key": "585",
    "_id": "txn/585",
    "_rev": "_gDzJN6i--D"
  },
  {
    "_key": "590",
    "_id": "txn/590",
    "_rev": "_gDzJN6m---"
  },
  {
    "_key": "594",
    "_id": "txn/594",
    "_rev": "_gDzJN6m--_"
  },
  {
    "_key": "600",
    "_id": "txn/600",
    "_rev": "_gDzJN6m--A"
  },
  {
    "_key": "604",
    "_id": "txn/604",
    "_rev": "_gDzJN6m--B"
  },
  {
    "_key": "605",
    "_id": "txn/605",
    "_rev": "_gDzJN6m--C"
  },
  {
    "_key": "609",
    "_id": "txn/609",
    "_rev": "_gDzJN6m--D"
  },
  {
    "_key": "611",
    "_id": "txn/611",
    "_rev": "_gDzJN6q---"
  },
  {
    "_key": "613",
    "_id": "txn/613",
    "_rev": "_gDzJN6q--_"
  },
  {
    "_key": "617",
    "_id": "txn/617",
    "_rev": "_gDzJN6q--A"
  },
  {
    "_key": "619",
    "_id": "txn/619",
    "_rev": "_gDzJN6q--B"
  },
  {
    "_key": "622",
    "_id": "txn/622",
    "_rev": "_gDzJN6q--C"
  },
  {
    "_key": "626",
    "_id": "txn/626",
    "_rev": "_gDzJN6q--D"
  },
  {
    "_key": "641",
    "_id": "txn/641",
    "_rev": "_gDzJN6q--E"
  },
  {
    "_key": "645",
    "_id": "txn/645",
    "_rev": "_gDzJN6q--F"
  },
  {
    "_key": "650",
    "_id": "txn/650",
    "_rev": "_gDzJN6u---"
  },
  {
    "_key": "654",
    "_id": "txn/654",
    "_rev": "_gDzJN6u--_"
  },
  {
    "_key": "655",
    "_id": "txn/655",
    "_rev": "_gDzJN6u--A"
  },
  {
    "_key": "657",
    "_id": "txn/657",
    "_rev": "_gDzJN6u--B"
  },
  {
    "_key": "664",
    "_id": "txn/664",
    "_rev": "_gDzJN6u--C"
  },
  {
    "_key": "667",
    "_id": "txn/667",
    "_rev": "_gDzJN6y---"
  },
  {
    "_key": "669",
    "_id": "txn/669",
    "_rev": "_gDzJN6y--_"
  },
  {
    "_key": "674",
    "_id": "txn/674",
    "_rev": "_gDzJN6y--A"
  },
  {
    "_key": "683",
    "_id": "txn/683",
    "_rev": "_gDzJN6y--B"
  },
  {
    "_key": "689",
    "_id": "txn/689",
    "_rev": "_gDzJN6y--C"
  },
  {
    "_key": "698",
    "_id": "txn/698",
    "_rev": "_gDzJN62---"
  },
  {
    "_key": "702",
    "_id": "txn/702",
    "_rev": "_gDzJN62--_"
  },
  {
    "_key": "703",
    "_id": "txn/703",
    "_rev": "_gDzJN62--A"
  },
  {
    "_key": "705",
    "_id": "txn/705",
    "_rev": "_gDzJN62--B"
  },
  {
    "_key": "711",
    "_id": "txn/711",
    "_rev": "_gDzJN62--C"
  },
  {
    "_key": "714",
    "_id": "txn/714",
    "_rev": "_gDzJN62--D"
  },
  {
    "_key": "719",
    "_id": "txn/719",
    "_rev": "_gDzJN66---"
  },
  {
    "_key": "723",
    "_id": "txn/723",
    "_rev": "_gDzJN66--_"
  },
  {
    "_key": "726",
    "_id": "txn/726",
    "_rev": "_gDzJN66--A"
  },
  {
    "_key": "736",
    "_id": "txn/736",
    "_rev": "_gDzJN66--B"
  },
  {
    "_key": "739",
    "_id": "txn/739",
    "_rev": "_gDzJN66--C"
  },
  {
    "_key": "741",
    "_id": "txn/741",
    "_rev": "_gDzJN66--D"
  },
  {
    "_key": "743",
    "_id": "txn/743",
    "_rev": "_gDzJN66--E"
  },
  {
    "_key": "744",
    "_id": "txn/744",
    "_rev": "_gDzJN66--F"
  },
  {
    "_key": "748",
    "_id": "txn/748",
    "_rev": "_gDzJN7----"
  },
  {
    "_key": "749",
    "_id": "txn/749",
    "_rev": "_gDzJN7---_"
  },
  {
    "_key": "753",
    "_id": "txn/753",
    "_rev": "_gDzJN7---A"
  },
  {
    "_key": "754",
    "_id": "txn/754",
    "_rev": "_gDzJN7---B"
  },
  {
    "_key": "758",
    "_id": "txn/758",
    "_rev": "_gDzJN7---C"
  },
  {
    "_key": "761",
    "_id": "txn/761",
    "_rev": "_gDzJN7---D"
  },
  {
    "_key": "767",
    "_id": "txn/767",
    "_rev": "_gDzJN7---E"
  },
  {
    "_key": "774",
    "_id": "txn/774",
    "_rev": "_gDzJN7---F"
  },
  {
    "_key": "779",
    "_id": "txn/779",
    "_rev": "_gDzJN7---G"
  },
  {
    "_key": "787",
    "_id": "txn/787",
    "_rev": "_gDzJN7C---"
  },
  {
    "_key": "791",
    "_id": "txn/791",
    "_rev": "_gDzJN7C--_"
  },
  {
    "_key": "795",
    "_id": "txn/795",
    "_rev": "_gDzJN7C--A"
  },
  {
    "_key": "796",
    "_id": "txn/796",
    "_rev": "_gDzJN7C--B"
  },
  {
    "_key": "803",
    "_id": "txn/803",
    "_rev": "_gDzJN7C--C"
  },
  {
    "_key": "805",
    "_id": "txn/805",
    "_rev": "_gDzJN7C--D"
  },
  {
    "_key": "810",
    "_id": "txn/810",
    "_rev": "_gDzJN7C--E"
  },
  {
    "_key": "812",
    "_id": "txn/812",
    "_rev": "_gDzJN7C--F"
  },
  {
    "_key": "816",
    "_id": "txn/816",
    "_rev": "_gDzJN7G---"
  },
  {
    "_key": "817",
    "_id": "txn/817",
    "_rev": "_gDzJN7G--_"
  },
  {
    "_key": "821",
    "_id": "txn/821",
    "_rev": "_gDzJN7G--A"
  },
  {
    "_key": "830",
    "_id": "txn/830",
    "_rev": "_gDzJN7G--B"
  },
  {
    "_key": "838",
    "_id": "txn/838",
    "_rev": "_gDzJN7G--C"
  },
  {
    "_key": "872",
    "_id": "txn/872",
    "_rev": "_gDzJN7G--D"
  },
  {
    "_key": "880",
    "_id": "txn/880",
    "_rev": "_gDzJN7G--E"
  },
  {
    "_key": "887",
    "_id": "txn/887",
    "_rev": "_gDzJN7G--F"
  },
  {
    "_key": "894",
    "_id": "txn/894",
    "_rev": "_gDzJN7K---"
  },
  {
    "_key": "900",
    "_id": "txn/900",
    "_rev": "_gDzJN7K--_"
  },
  {
    "_key": "903",
    "_id": "txn/903",
    "_rev": "_gDzJN7K--A"
  },
  {
    "_key": "904",
    "_id": "txn/904",
    "_rev": "_gDzJN7K--B"
  },
  {
    "_key": "912",
    "_id": "txn/912",
    "_rev": "_gDzJN7K--C"
  },
  {
    "_key": "916",
    "_id": "txn/916",
    "_rev": "_gDzJN7K--D"
  },
  {
    "_key": "919",
    "_id": "txn/919",
    "_rev": "_gDzJN7K--E"
  },
  {
    "_key": "927",
    "_id": "txn/927",
    "_rev": "_gDzJN7K--F"
  },
  {
    "_key": "928",
    "_id": "txn/928",
    "_rev": "_gDzJN7O---"
  },
  {
    "_key": "931",
    "_id": "txn/931",
    "_rev": "_gDzJN7O--_"
  },
  {
    "_key": "935",
    "_id": "txn/935",
    "_rev": "_gDzJN7O--A"
  },
  {
    "_key": "940",
    "_id": "txn/940",
    "_rev": "_gDzJN7O--B"
  },
  {
    "_key": "944",
    "_id": "txn/944",
    "_rev": "_gDzJN7O--C"
  },
  {
    "_key": "949",
    "_id": "txn/949",
    "_rev": "_gDzJN7O--D"
  },
  {
    "_key": "950",
    "_id": "txn/950",
    "_rev": "_gDzJN7O--E"
  },
  {
    "_key": "953",
    "_id": "txn/953",
    "_rev": "_gDzJN7S---"
  },
  {
    "_key": "957",
    "_id": "txn/957",
    "_rev": "_gDzJN7S--_"
  },
  {
    "_key": "968",
    "_id": "txn/968",
    "_rev": "_gDzJN7S--A"
  },
  {
    "_key": "970",
    "_id": "txn/970",
    "_rev": "_gDzJN7S--B"
  },
  {
    "_key": "977",
    "_id": "txn/977",
    "_rev": "_gDzJN7S--C"
  },
  {
    "_key": "979",
    "_id": "txn/979",
    "_rev": "_gDzJN7W---"
  },
  {
    "_key": "981",
    "_id": "txn/981",
    "_rev": "_gDzJN7W--_"
  },
  {
    "_key": "986",
    "_id": "txn/986",
    "_rev": "_gDzJN7W--A"
  },
  {
    "_key": "987",
    "_id": "txn/987",
    "_rev": "_gDzJN7W--B"
  },
  {
    "_key": "990",
    "_id": "txn/990",
    "_rev": "_gDzJN7W--C"
  },
  {
    "_key": "994",
    "_id": "txn/994",
    "_rev": "_gDzJN7W--D"
  },
  {
    "_key": "995",
    "_id": "txn/995",
    "_rev": "_gDzJN7W--E"
  },
  {
    "_key": "999",
    "_id": "txn/999",
    "_rev": "_gDzJN7W--F"
  },
  {
    "_key": "1003",
    "_id": "txn/1003",
    "_rev": "_gDzJN7a---"
  },
  {
    "_key": "1009",
    "_id": "txn/1009",
    "_rev": "_gDzJN7a--_"
  },
  {
    "_key": "1010",
    "_id": "txn/1010",
    "_rev": "_gDzJN7a--A"
  },
  {
    "_key": "1013",
    "_id": "txn/1013",
    "_rev": "_gDzJN7a--B"
  },
  {
    "_key": "1017",
    "_id": "txn/1017",
    "_rev": "_gDzJN7a--C"
  },
  {
    "_key": "1020",
    "_id": "txn/1020",
    "_rev": "_gDzJN7a--D"
  },
  {
    "_key": "1023",
    "_id": "txn/1023",
    "_rev": "_gDzJN7a--E"
  },
  {
    "_key": "1027",
    "_id": "txn/1027",
    "_rev": "_gDzJN7a--F"
  },
  {
    "_key": "1031",
    "_id": "txn/1031",
    "_rev": "_gDzJN7a--G"
  },
  {
    "_key": "1034",
    "_id": "txn/1034",
    "_rev": "_gDzJN7e---"
  },
  {
    "_key": "1041",
    "_id": "txn/1041",
    "_rev": "_gDzJN7e--_"
  },
  {
    "_key": "1043",
    "_id": "txn/1043",
    "_rev": "_gDzJN7e--A"
  },
  {
    "_key": "1047",
    "_id": "txn/1047",
    "_rev": "_gDzJN7e--B"
  },
  {
    "_key": "1057",
    "_id": "txn/1057",
    "_rev": "_gDzJN7e--C"
  },
  {
    "_key": "1060",
    "_id": "txn/1060",
    "_rev": "_gDzJN7e--D"
  },
  {
    "_key": "1065",
    "_id": "txn/1065",
    "_rev": "_gDzJN7e--E"
  },
  {
    "_key": "1069",
    "_id": "txn/1069",
    "_rev": "_gDzJN7e--F"
  },
  {
    "_key": "1071",
    "_id": "txn/1071",
    "_rev": "_gDzJN7e--G"
  },
  {
    "_key": "1075",
    "_id": "txn/1075",
    "_rev": "_gDzJN7i---"
  },
  {
    "_key": "1081",
    "_id": "txn/1081",
    "_rev": "_gDzJN7i--_"
  },
  {
    "_key": "1085",
    "_id": "txn/1085",
    "_rev": "_gDzJN7i--A"
  },
  {
    "_key": "1088",
    "_id": "txn/1088",
    "_rev": "_gDzJN7i--B"
  },
  {
    "_key": "1091",
    "_id": "txn/1091",
    "_rev": "_gDzJN7i--C"
  },
  {
    "_key": "1093",
    "_id": "txn/1093",
    "_rev": "_gDzJN7i--D"
  },
  {
    "_key": "1099",
    "_id": "txn/1099",
    "_rev": "_gDzJN7i--E"
  },
  {
    "_key": "1101",
    "_id": "txn/1101",
    "_rev": "_gDzJN7i--F"
  },
  {
    "_key": "1108",
    "_id": "txn/1108",
    "_rev": "_gDzJN7m---"
  },
  {
    "_key": "1110",
    "_id": "txn/1110",
    "_rev": "_gDzJN7m--_"
  },
  {
    "_key": "1114",
    "_id": "txn/1114",
    "_rev": "_gDzJN7m--A"
  },
  {
    "_key": "1117",
    "_id": "txn/1117",
    "_rev": "_gDzJN7m--B"
  },
  {
    "_key": "1122",
    "_id": "txn/1122",
    "_rev": "_gDzJN7m--C"
  },
  {
    "_key": "1124",
    "_id": "txn/1124",
    "_rev": "_gDzJN7m--D"
  },
  {
    "_key": "1128",
    "_id": "txn/1128",
    "_rev": "_gDzJN7m--E"
  },
  {
    "_key": "1137",
    "_id": "txn/1137",
    "_rev": "_gDzJN7q---"
  },
  {
    "_key": "1146",
    "_id": "txn/1146",
    "_rev": "_gDzJN7q--_"
  },
  {
    "_key": "1149",
    "_id": "txn/1149",
    "_rev": "_gDzJN7q--A"
  },
  {
    "_key": "1151",
    "_id": "txn/1151",
    "_rev": "_gDzJN7q--B"
  },
  {
    "_key": "1161",
    "_id": "txn/1161",
    "_rev": "_gDzJN7q--C"
  },
  {
    "_key": "1163",
    "_id": "txn/1163",
    "_rev": "_gDzJN7q--D"
  },
  {
    "_key": "1165",
    "_id": "txn/1165",
    "_rev": "_gDzJN7u---"
  },
  {
    "_key": "1168",
    "_id": "txn/1168",
    "_rev": "_gDzJN7u--_"
  },
  {
    "_key": "1172",
    "_id": "txn/1172",
    "_rev": "_gDzJN7u--A"
  },
  {
    "_key": "1174",
    "_id": "txn/1174",
    "_rev": "_gDzJN7u--B"
  },
  {
    "_key": "1179",
    "_id": "txn/1179",
    "_rev": "_gDzJN7u--C"
  },
  {
    "_key": "1185",
    "_id": "txn/1185",
    "_rev": "_gDzJN7u--D"
  },
  {
    "_key": "1187",
    "_id": "txn/1187",
    "_rev": "_gDzJN7u--E"
  },
  {
    "_key": "1192",
    "_id": "txn/1192",
    "_rev": "_gDzJN7y---"
  },
  {
    "_key": "1194",
    "_id": "txn/1194",
    "_rev": "_gDzJN7y--_"
  },
  {
    "_key": "1196",
    "_id": "txn/1196",
    "_rev": "_gDzJN7y--A"
  },
  {
    "_key": "1200",
    "_id": "txn/1200",
    "_rev": "_gDzJN7y--B"
  },
  {
    "_key": "1204",
    "_id": "txn/1204",
    "_rev": "_gDzJN7y--C"
  },
  {
    "_key": "1205",
    "_id": "txn/1205",
    "_rev": "_gDzJN7y--D"
  },
  {
    "_key": "1207",
    "_id": "txn/1207",
    "_rev": "_gDzJN7y--E"
  },
  {
    "_key": "1210",
    "_id": "txn/1210",
    "_rev": "_gDzJN72---"
  },
  {
    "_key": "1211",
    "_id": "txn/1211",
    "_rev": "_gDzJN72--_"
  },
  {
    "_key": "1214",
    "_id": "txn/1214",
    "_rev": "_gDzJN72--A"
  },
  {
    "_key": "1216",
    "_id": "txn/1216",
    "_rev": "_gDzJN72--B"
  },
  {
    "_key": "1221",
    "_id": "txn/1221",
    "_rev": "_gDzJN72--C"
  },
  {
    "_key": "1230",
    "_id": "txn/1230",
    "_rev": "_gDzJN72--D"
  },
  {
    "_key": "1234",
    "_id": "txn/1234",
    "_rev": "_gDzJN76---"
  },
  {
    "_key": "1238",
    "_id": "txn/1238",
    "_rev": "_gDzJN76--_"
  },
  {
    "_key": "1239",
    "_id": "txn/1239",
    "_rev": "_gDzJN76--A"
  },
  {
    "_key": "1246",
    "_id": "txn/1246",
    "_rev": "_gDzJN76--B"
  },
  {
    "_key": "1247",
    "_id": "txn/1247",
    "_rev": "_gDzJN76--C"
  },
  {
    "_key": "1251",
    "_id": "txn/1251",
    "_rev": "_gDzJN76--D"
  },
  {
    "_key": "1256",
    "_id": "txn/1256",
    "_rev": "_gDzJN76--E"
  },
  {
    "_key": "1259",
    "_id": "txn/1259",
    "_rev": "_gDzJN76--F"
  },
  {
    "_key": "1261",
    "_id": "txn/1261",
    "_rev": "_gDzJN8----"
  },
  {
    "_key": "1265",
    "_id": "txn/1265",
    "_rev": "_gDzJN8---_"
  },
  {
    "_key": "1268",
    "_id": "txn/1268",
    "_rev": "_gDzJN8---A"
  },
  {
    "_key": "1269",
    "_id": "txn/1269",
    "_rev": "_gDzJN8---B"
  },
  {
    "_key": "1273",
    "_id": "txn/1273",
    "_rev": "_gDzJN8---C"
  },
  {
    "_key": "1278",
    "_id": "txn/1278",
    "_rev": "_gDzJN8---D"
  },
  {
    "_key": "1285",
    "_id": "txn/1285",
    "_rev": "_gDzJN8---E"
  },
  {
    "_key": "1293",
    "_id": "txn/1293",
    "_rev": "_gDzJN8---F"
  },
  {
    "_key": "1296",
    "_id": "txn/1296",
    "_rev": "_gDzJN8C---"
  },
  {
    "_key": "1303",
    "_id": "txn/1303",
    "_rev": "_gDzJN8C--_"
  },
  {
    "_key": "1308",
    "_id": "txn/1308",
    "_rev": "_gDzJN8C--A"
  },
  {
    "_key": "1316",
    "_id": "txn/1316",
    "_rev": "_gDzJN8C--B"
  },
  {
    "_key": "1323",
    "_id": "txn/1323",
    "_rev": "_gDzJN8C--C"
  },
  {
    "_key": "1328",
    "_id": "txn/1328",
    "_rev": "_gDzJN8C--D"
  },
  {
    "_key": "1330",
    "_id": "txn/1330",
    "_rev": "_gDzJN8C--E"
  },
  {
    "_key": "1335",
    "_id": "txn/1335",
    "_rev": "_gDzJN8C--F"
  },
  {
    "_key": "1338",
    "_id": "txn/1338",
    "_rev": "_gDzJN8G---"
  },
  {
    "_key": "1343",
    "_id": "txn/1343",
    "_rev": "_gDzJN8G--_"
  },
  {
    "_key": "1348",
    "_id": "txn/1348",
    "_rev": "_gDzJN8G--A"
  },
  {
    "_key": "1349",
    "_id": "txn/1349",
    "_rev": "_gDzJN8G--B"
  },
  {
    "_key": "1357",
    "_id": "txn/1357",
    "_rev": "_gDzJN8G--C"
  },
  {
    "_key": "1361",
    "_id": "txn/1361",
    "_rev": "_gDzJN8G--D"
  },
  {
    "_key": "1369",
    "_id": "txn/1369",
    "_rev": "_gDzJN8G--E"
  },
  {
    "_key": "1371",
    "_id": "txn/1371",
    "_rev": "_gDzJN8K---"
  },
  {
    "_key": "1375",
    "_id": "txn/1375",
    "_rev": "_gDzJN8K--_"
  },
  {
    "_key": "1378",
    "_id": "txn/1378",
    "_rev": "_gDzJN8K--A"
  },
  {
    "_key": "1382",
    "_id": "txn/1382",
    "_rev": "_gDzJN8K--B"
  },
  {
    "_key": "1384",
    "_id": "txn/1384",
    "_rev": "_gDzJN8K--C"
  },
  {
    "_key": "1387",
    "_id": "txn/1387",
    "_rev": "_gDzJN8K--D"
  },
  {
    "_key": "1390",
    "_id": "txn/1390",
    "_rev": "_gDzJN8K--E"
  },
  {
    "_key": "1394",
    "_id": "txn/1394",
    "_rev": "_gDzJN8K--F"
  },
  {
    "_key": "1400",
    "_id": "txn/1400",
    "_rev": "_gDzJN8O---"
  },
  {
    "_key": "1404",
    "_id": "txn/1404",
    "_rev": "_gDzJN8O--_"
  },
  {
    "_key": "1411",
    "_id": "txn/1411",
    "_rev": "_gDzJN8O--A"
  },
  {
    "_key": "1414",
    "_id": "txn/1414",
    "_rev": "_gDzJN8S---"
  },
  {
    "_key": "1419",
    "_id": "txn/1419",
    "_rev": "_gDzJN8S--_"
  },
  {
    "_key": "1424",
    "_id": "txn/1424",
    "_rev": "_gDzJN8S--A"
  },
  {
    "_key": "1429",
    "_id": "txn/1429",
    "_rev": "_gDzJN8S--B"
  },
  {
    "_key": "1439",
    "_id": "txn/1439",
    "_rev": "_gDzJN8S--C"
  },
  {
    "_key": "1441",
    "_id": "txn/1441",
    "_rev": "_gDzJN8S--D"
  },
  {
    "_key": "1460",
    "_id": "txn/1460",
    "_rev": "_gDzJN8S--E"
  },
  {
    "_key": "1464",
    "_id": "txn/1464",
    "_rev": "_gDzJN8W---"
  },
  {
    "_key": "1468",
    "_id": "txn/1468",
    "_rev": "_gDzJN8W--_"
  },
  {
    "_key": "1475",
    "_id": "txn/1475",
    "_rev": "_gDzJN8W--A"
  },
  {
    "_key": "1476",
    "_id": "txn/1476",
    "_rev": "_gDzJN8W--B"
  },
  {
    "_key": "1482",
    "_id": "txn/1482",
    "_rev": "_gDzJN8W--C"
  },
  {
    "_key": "1486",
    "_id": "txn/1486",
    "_rev": "_gDzJN8W--D"
  },
  {
    "_key": "1491",
    "_id": "txn/1491",
    "_rev": "_gDzJN8W--E"
  },
  {
    "_key": "1500",
    "_id": "txn/1500",
    "_rev": "_gDzJN8a---"
  },
  {
    "_key": "1502",
    "_id": "txn/1502",
    "_rev": "_gDzJN8a--_"
  },
  {
    "_key": "1504",
    "_id": "txn/1504",
    "_rev": "_gDzJN8a--A"
  },
  {
    "_key": "1507",
    "_id": "txn/1507",
    "_rev": "_gDzJN8a--B"
  },
  {
    "_key": "1510",
    "_id": "txn/1510",
    "_rev": "_gDzJN8a--C"
  },
  {
    "_key": "1512",
    "_id": "txn/1512",
    "_rev": "_gDzJN8a--D"
  },
  {
    "_key": "1518",
    "_id": "txn/1518",
    "_rev": "_gDzJN8a--E"
  },
  {
    "_key": "1520",
    "_id": "txn/1520",
    "_rev": "_gDzJN8a--F"
  },
  {
    "_key": "1524",
    "_id": "txn/1524",
    "_rev": "_gDzJN8a--G"
  },
  {
    "_key": "1528",
    "_id": "txn/1528",
    "_rev": "_gDzJN8e---"
  },
  {
    "_key": "1529",
    "_id": "txn/1529",
    "_rev": "_gDzJN8e--_"
  },
  {
    "_key": "1534",
    "_id": "txn/1534",
    "_rev": "_gDzJN8e--A"
  },
  {
    "_key": "1537",
    "_id": "txn/1537",
    "_rev": "_gDzJN8e--B"
  },
  {
    "_key": "1538",
    "_id": "txn/1538",
    "_rev": "_gDzJN8e--C"
  },
  {
    "_key": "1543",
    "_id": "txn/1543",
    "_rev": "_gDzJN8e--D"
  },
  {
    "_key": "1545",
    "_id": "txn/1545",
    "_rev": "_gDzJN8e--E"
  },
  {
    "_key": "1549",
    "_id": "txn/1549",
    "_rev": "_gDzJN8e--F"
  },
  {
    "_key": "1552",
    "_id": "txn/1552",
    "_rev": "_gDzJN8i---"
  },
  {
    "_key": "1554",
    "_id": "txn/1554",
    "_rev": "_gDzJN8i--_"
  },
  {
    "_key": "1557",
    "_id": "txn/1557",
    "_rev": "_gDzJN8i--A"
  },
  {
    "_key": "1559",
    "_id": "txn/1559",
    "_rev": "_gDzJN8i--B"
  },
  {
    "_key": "1563",
    "_id": "txn/1563",
    "_rev": "_gDzJN8i--C"
  },
  {
    "_key": "1566",
    "_id": "txn/1566",
    "_rev": "_gDzJN8i--D"
  },
  {
    "_key": "1568",
    "_id": "txn/1568",
    "_rev": "_gDzJN8i--E"
  },
  {
    "_key": "1571",
    "_id": "txn/1571",
    "_rev": "_gDzJN8i--F"
  },
  {
    "_key": "1577",
    "_id": "txn/1577",
    "_rev": "_gDzJN8i--G"
  },
  {
    "_key": "1578",
    "_id": "txn/1578",
    "_rev": "_gDzJN8m---"
  },
  {
    "_key": "1581",
    "_id": "txn/1581",
    "_rev": "_gDzJN8m--_"
  },
  {
    "_key": "1587",
    "_id": "txn/1587",
    "_rev": "_gDzJN8m--A"
  },
  {
    "_key": "1588",
    "_id": "txn/1588",
    "_rev": "_gDzJN8m--B"
  },
  {
    "_key": "1592",
    "_id": "txn/1592",
    "_rev": "_gDzJN8m--C"
  },
  {
    "_key": "1597",
    "_id": "txn/1597",
    "_rev": "_gDzJN8m--D"
  },
  {
    "_key": "1600",
    "_id": "txn/1600",
    "_rev": "_gDzJN8q---"
  },
  {
    "_key": "1602",
    "_id": "txn/1602",
    "_rev": "_gDzJN8q--_"
  },
  {
    "_key": "1603",
    "_id": "txn/1603",
    "_rev": "_gDzJN8q--A"
  },
  {
    "_key": "1608",
    "_id": "txn/1608",
    "_rev": "_gDzJN8q--B"
  },
  {
    "_key": "1614",
    "_id": "txn/1614",
    "_rev": "_gDzJN8q--C"
  },
  {
    "_key": "1618",
    "_id": "txn/1618",
    "_rev": "_gDzJN8q--D"
  },
  {
    "_key": "1620",
    "_id": "txn/1620",
    "_rev": "_gDzJN8q--E"
  },
  {
    "_key": "1625",
    "_id": "txn/1625",
    "_rev": "_gDzJN8u---"
  },
  {
    "_key": "1629",
    "_id": "txn/1629",
    "_rev": "_gDzJN8u--_"
  },
  {
    "_key": "1633",
    "_id": "txn/1633",
    "_rev": "_gDzJN8u--A"
  },
  {
    "_key": "1635",
    "_id": "txn/1635",
    "_rev": "_gDzJN8u--B"
  },
  {
    "_key": "1639",
    "_id": "txn/1639",
    "_rev": "_gDzJN8u--C"
  },
  {
    "_key": "1642",
    "_id": "txn/1642",
    "_rev": "_gDzJN8u--D"
  },
  {
    "_key": "1645",
    "_id": "txn/1645",
    "_rev": "_gDzJN8u--E"
  },
  {
    "_key": "1648",
    "_id": "txn/1648",
    "_rev": "_gDzJN8y---"
  },
  {
    "_key": "1651",
    "_id": "txn/1651",
    "_rev": "_gDzJN8y--_"
  },
  {
    "_key": "1655",
    "_id": "txn/1655",
    "_rev": "_gDzJN8y--A"
  },
  {
    "_key": "1660",
    "_id": "txn/1660",
    "_rev": "_gDzJN8y--B"
  },
  {
    "_key": "1661",
    "_id": "txn/1661",
    "_rev": "_gDzJN8y--C"
  },
  {
    "_key": "1666",
    "_id": "txn/1666",
    "_rev": "_gDzJN8y--D"
  },
  {
    "_key": "1673",
    "_id": "txn/1673",
    "_rev": "_gDzJN8y--E"
  },
  {
    "_key": "1678",
    "_id": "txn/1678",
    "_rev": "_gDzJN82---"
  },
  {
    "_key": "1682",
    "_id": "txn/1682",
    "_rev": "_gDzJN82--_"
  },
  {
    "_key": "1687",
    "_id": "txn/1687",
    "_rev": "_gDzJN82--A"
  },
  {
    "_key": "1690",
    "_id": "txn/1690",
    "_rev": "_gDzJN82--B"
  },
  {
    "_key": "1694",
    "_id": "txn/1694",
    "_rev": "_gDzJN82--C"
  },
  {
    "_key": "1698",
    "_id": "txn/1698",
    "_rev": "_gDzJN82--D"
  },
  {
    "_key": "1702",
    "_id": "txn/1702",
    "_rev": "_gDzJN86---"
  },
  {
    "_key": "1705",
    "_id": "txn/1705",
    "_rev": "_gDzJN86--_"
  },
  {
    "_key": "1710",
    "_id": "txn/1710",
    "_rev": "_gDzJN86--A"
  },
  {
    "_key": "1718",
    "_id": "txn/1718",
    "_rev": "_gDzJN86--B"
  },
  {
    "_key": "1719",
    "_id": "txn/1719",
    "_rev": "_gDzJN9----"
  },
  {
    "_key": "1722",
    "_id": "txn/1722",
    "_rev": "_gDzJN9---_"
  },
  {
    "_key": "1723",
    "_id": "txn/1723",
    "_rev": "_gDzJN9---A"
  },
  {
    "_key": "1725",
    "_id": "txn/1725",
    "_rev": "_gDzJN9---B"
  },
  {
    "_key": "1727",
    "_id": "txn/1727",
    "_rev": "_gDzJN9---C"
  },
  {
    "_key": "1729",
    "_id": "txn/1729",
    "_rev": "_gDzJN9---D"
  },
  {
    "_key": "1731",
    "_id": "txn/1731",
    "_rev": "_gDzJN9---E"
  },
  {
    "_key": "1734",
    "_id": "txn/1734",
    "_rev": "_gDzJN9---F"
  },
  {
    "_key": "1735",
    "_id": "txn/1735",
    "_rev": "_gDzJN9C---"
  },
  {
    "_key": "1740",
    "_id": "txn/1740",
    "_rev": "_gDzJN9C--_"
  },
  {
    "_key": "1746",
    "_id": "txn/1746",
    "_rev": "_gDzJN9C--A"
  },
  {
    "_key": "1752",
    "_id": "txn/1752",
    "_rev": "_gDzJN9C--B"
  },
  {
    "_key": "1757",
    "_id": "txn/1757",
    "_rev": "_gDzJN9C--C"
  },
  {
    "_key": "1764",
    "_id": "txn/1764",
    "_rev": "_gDzJN9C--D"
  },
  {
    "_key": "1768",
    "_id": "txn/1768",
    "_rev": "_gDzJN9C--E"
  },
  {
    "_key": "1771",
    "_id": "txn/1771",
    "_rev": "_gDzJN9C--F"
  },
  {
    "_key": "1775",
    "_id": "txn/1775",
    "_rev": "_gDzJN9G---"
  },
  {
    "_key": "1779",
    "_id": "txn/1779",
    "_rev": "_gDzJN9G--_"
  },
  {
    "_key": "1784",
    "_id": "txn/1784",
    "_rev": "_gDzJN9G--A"
  },
  {
    "_key": "1793",
    "_id": "txn/1793",
    "_rev": "_gDzJN9G--B"
  },
  {
    "_key": "1794",
    "_id": "txn/1794",
    "_rev": "_gDzJN9G--C"
  },
  {
    "_key": "1801",
    "_id": "txn/1801",
    "_rev": "_gDzJN9G--D"
  },
  {
    "_key": "1804",
    "_id": "txn/1804",
    "_rev": "_gDzJN9G--E"
  },
  {
    "_key": "1808",
    "_id": "txn/1808",
    "_rev": "_gDzJN9K---"
  },
  {
    "_key": "1812",
    "_id": "txn/1812",
    "_rev": "_gDzJN9K--_"
  },
  {
    "_key": "1815",
    "_id": "txn/1815",
    "_rev": "_gDzJN9K--A"
  },
  {
    "_key": "1820",
    "_id": "txn/1820",
    "_rev": "_gDzJN9K--B"
  },
  {
    "_key": "1824",
    "_id": "txn/1824",
    "_rev": "_gDzJN9K--C"
  },
  {
    "_key": "1825",
    "_id": "txn/1825",
    "_rev": "_gDzJN9K--D"
  },
  {
    "_key": "1831",
    "_id": "txn/1831",
    "_rev": "_gDzJN9K--E"
  },
  {
    "_key": "1835",
    "_id": "txn/1835",
    "_rev": "_gDzJN9K--F"
  },
  {
    "_key": "1838",
    "_id": "txn/1838",
    "_rev": "_gDzJN9K--G"
  },
  {
    "_key": "1841",
    "_id": "txn/1841",
    "_rev": "_gDzJN9O---"
  },
  {
    "_key": "1843",
    "_id": "txn/1843",
    "_rev": "_gDzJN9O--_"
  },
  {
    "_key": "1845",
    "_id": "txn/1845",
    "_rev": "_gDzJN9O--A"
  },
  {
    "_key": "1849",
    "_id": "txn/1849",
    "_rev": "_gDzJN9O--B"
  },
  {
    "_key": "1850",
    "_id": "txn/1850",
    "_rev": "_gDzJN9O--C"
  },
  {
    "_key": "1853",
    "_id": "txn/1853",
    "_rev": "_gDzJN9O--D"
  },
  {
    "_key": "1858",
    "_id": "txn/1858",
    "_rev": "_gDzJN9O--E"
  },
  {
    "_key": "1864",
    "_id": "txn/1864",
    "_rev": "_gDzJN9O--F"
  },
  {
    "_key": "1872",
    "_id": "txn/1872",
    "_rev": "_gDzJN9S---"
  },
  {
    "_key": "1874",
    "_id": "txn/1874",
    "_rev": "_gDzJN9S--_"
  },
  {
    "_key": "1875",
    "_id": "txn/1875",
    "_rev": "_gDzJN9S--A"
  },
  {
    "_key": "1878",
    "_id": "txn/1878",
    "_rev": "_gDzJN9S--B"
  },
  {
    "_key": "1883",
    "_id": "txn/1883",
    "_rev": "_gDzJN9S--C"
  },
  {
    "_key": "1892",
    "_id": "txn/1892",
    "_rev": "_gDzJN9S--D"
  },
  {
    "_key": "1895",
    "_id": "txn/1895",
    "_rev": "_gDzJN9S--E"
  },
  {
    "_key": "1901",
    "_id": "txn/1901",
    "_rev": "_gDzJN9S--F"
  },
  {
    "_key": "1906",
    "_id": "txn/1906",
    "_rev": "_gDzJN9W---"
  },
  {
    "_key": "1915",
    "_id": "txn/1915",
    "_rev": "_gDzJN9W--_"
  },
  {
    "_key": "1918",
    "_id": "txn/1918",
    "_rev": "_gDzJN9W--A"
  },
  {
    "_key": "1921",
    "_id": "txn/1921",
    "_rev": "_gDzJN9W--B"
  },
  {
    "_key": "1927",
    "_id": "txn/1927",
    "_rev": "_gDzJN9W--C"
  },
  {
    "_key": "1929",
    "_id": "txn/1929",
    "_rev": "_gDzJN9W--D"
  },
  {
    "_key": "1933",
    "_id": "txn/1933",
    "_rev": "_gDzJN9W--E"
  },
  {
    "_key": "1935",
    "_id": "txn/1935",
    "_rev": "_gDzJN9W--F"
  },
  {
    "_key": "1943",
    "_id": "txn/1943",
    "_rev": "_gDzJN9W--G"
  },
  {
    "_key": "1947",
    "_id": "txn/1947",
    "_rev": "_gDzJN9a---"
  },
  {
    "_key": "1950",
    "_id": "txn/1950",
    "_rev": "_gDzJN9a--_"
  },
  {
    "_key": "1951",
    "_id": "txn/1951",
    "_rev": "_gDzJN9a--A"
  },
  {
    "_key": "1954",
    "_id": "txn/1954",
    "_rev": "_gDzJN9a--B"
  },
  {
    "_key": "1959",
    "_id": "txn/1959",
    "_rev": "_gDzJN9a--C"
  },
  {
    "_key": "1962",
    "_id": "txn/1962",
    "_rev": "_gDzJN9a--D"
  },
  {
    "_key": "1965",
    "_id": "txn/1965",
    "_rev": "_gDzJN9a--E"
  },
  {
    "_key": "1971",
    "_id": "txn/1971",
    "_rev": "_gDzJN9a--F"
  },
  {
    "_key": "1977",
    "_id": "txn/1977",
    "_rev": "_gDzJN9a--G"
  }
]